magicov/__init__.py
magicov-0.1.dist-info/COPYING
magicov-0.1.dist-info/METADATA
magicov-0.1.dist-info/WHEEL
magicov-0.1.dist-info/entry_points.txt
magicov-0.1.dist-info/top_level.txt
magicov-0.1.dist-info/RECORD
