Metadata-Version: 2.1
Name: magicov
Version: 0.1
Summary: UNKNOWN
Home-page: https://github.com/cript0nauta/magicov
Author: Matías Lang
Author-email: UNKNOWN
License: GPLv3+
Platform: UNKNOWN
Requires-Dist: google-pasta
Requires-Dist: coverage
